variantgrid_api/api_client.py
variantgrid_api/data_models.py
variantgrid_api-1.0.0.dist-info/licenses/LICENSE
variantgrid_api-1.0.0.dist-info/METADATA
variantgrid_api-1.0.0.dist-info/WHEEL
variantgrid_api-1.0.0.dist-info/top_level.txt
variantgrid_api-1.0.0.dist-info/RECORD
