Metadata-Version: 2.4
Name: variantgrid_api
Version: 1.0.0
Summary: A Python API client for VariantGrid
Author-email: Dave Lawrence <davmlaw@gmail.com>
License: MIT License
Project-URL: Homepage, https://github.com/SACGF/variantgrid_api
Classifier: Development Status :: 3 - Alpha
Classifier: Intended Audience :: Developers
Classifier: License :: OSI Approved :: MIT License
Classifier: Programming Language :: Python :: 3
Requires-Python: >=3.8
License-File: LICENSE
Requires-Dist: requests
Requires-Dist: dataclasses-json
Requires-Dist: samshee
Dynamic: license-file
